kensho_kfinance-4.1.2.dist-info/licenses/AUTHORS.md
kensho_kfinance-4.1.2.dist-info/licenses/LICENSE
kfinance/CHANGELOG.md
kfinance/__init__.py
kfinance/conftest.py
kfinance/mcp.py
kfinance/py.typed
kfinance/version.py
kfinance/client/README.md
kfinance/client/__init__.py
kfinance/client/batch_request_handling.py
kfinance/client/fetch.py
kfinance/client/industry_models.py
kfinance/client/kfinance.py
kfinance/client/meta_classes.py
kfinance/client/permission_models.py
kfinance/client/server_thread.py
kfinance/client/models/__init__.py
kfinance/client/models/currency_models.py
kfinance/client/models/date_and_period_models.py
kfinance/client/models/decimal_with_unit.py
kfinance/client/models/response_models.py
kfinance/client/models/tests/__init__.py
kfinance/client/models/tests/test_decimal_with_unit.py
kfinance/client/tests/__init__.py
kfinance/client/tests/test_batch_requests.py
kfinance/client/tests/test_client.py
kfinance/client/tests/test_fetch.py
kfinance/client/tests/test_group_objects.py
kfinance/client/tests/test_objects.py
kfinance/domains/README.md
kfinance/domains/__init__.py
kfinance/domains/business_relationships/__init__.py
kfinance/domains/business_relationships/business_relationship_models.py
kfinance/domains/business_relationships/business_relationship_tools.py
kfinance/domains/business_relationships/tests/__init__.py
kfinance/domains/business_relationships/tests/test_business_relationship_tools.py
kfinance/domains/capitalizations/__init__.py
kfinance/domains/capitalizations/capitalization_models.py
kfinance/domains/capitalizations/capitalization_tools.py
kfinance/domains/capitalizations/tests/__init__.py
kfinance/domains/capitalizations/tests/test_capitalization_models.py
kfinance/domains/capitalizations/tests/test_capitalization_tools.py
kfinance/domains/companies/__init__.py
kfinance/domains/companies/company_identifiers.py
kfinance/domains/companies/company_models.py
kfinance/domains/companies/company_tools.py
kfinance/domains/companies/tests/__init__.py
kfinance/domains/companies/tests/test_company_tools.py
kensho_kfinance-4.1.2.dist-info/METADATA
kensho_kfinance-4.1.2.dist-info/WHEEL
kensho_kfinance-4.1.2.dist-info/top_level.txt
kensho_kfinance-4.1.2.dist-info/RECORD
