Metadata-Version: 2.4
Name: kensho-kfinance
Version: 4.1.2
Summary: Python CLI for kFinance
Author-email: Luke Brown <luke.brown@kensho.com>, Michelle Keoy <michelle.keoy@kensho.com>, Keith Page <keith.page@kensho.com>, Matthew Rosen <matthew.rosen@kensho.com>, Nick Roshdieh <nick.roshdieh@kensho.com>
Project-URL: source, https://github.com/kensho-technologies/kfinance
Project-URL: changelog, https://github.com/kensho-technologies/kfinance/blob/main/kfinance/CHANGELOG.md
Project-URL: documentation, https://docs.kensho.com/llmreadyapi/python-library
Classifier: Programming Language :: Python :: 3
Classifier: Operating System :: OS Independent
Requires-Python: >=3.10
License-File: LICENSE
License-File: AUTHORS.md
Requires-Dist: cachetools<7,>=6
Requires-Dist: click<=9,>=8.2.1
Requires-Dist: fastmcp<2.14,>=2.13.1
Requires-Dist: langchain-core>=0.3.15
Requires-Dist: langchain-google-genai<3,>=2.1.5
Requires-Dist: numpy>=1.22.4
Requires-Dist: pandas>=2.0.0
Requires-Dist: pillow>=10
Requires-Dist: pydantic<3,>=2.10.0
Requires-Dist: pyjwt>=2.8.0
Requires-Dist: python-dateutil<2.9,>=2.8.2
Requires-Dist: strenum>=0.4.15
Requires-Dist: tabulate>=0.9.0
Requires-Dist: types-requests<3,>=2.22.0
Requires-Dist: requests<3,>=2.22.0
Requires-Dist: urllib3>=2.5
Provides-Extra: dev
Requires-Dist: coverage<8,>=7.6.10; extra == "dev"
Requires-Dist: ipykernel<7,>=6.29; extra == "dev"
Requires-Dist: langchain-anthropic<1,>=0.3.10; extra == "dev"
Requires-Dist: mypy<2,>=1.16.0; extra == "dev"
Requires-Dist: nbconvert<8,>=7.16; extra == "dev"
Requires-Dist: nbformat<6,>5.10; extra == "dev"
Requires-Dist: nbqa<2,>1.9; extra == "dev"
Requires-Dist: pytest<7,>=6.1.2; extra == "dev"
Requires-Dist: pytest-cov<7,>=6.0.0; extra == "dev"
Requires-Dist: requests_mock<2,>=1.12; extra == "dev"
Requires-Dist: ruff<1,>=0.9.4; extra == "dev"
Requires-Dist: time_machine<3,>=2.1; extra == "dev"
Requires-Dist: types-cachetools<6,>=5.5; extra == "dev"
Dynamic: license-file
